Workbook

Sheet Start Here
A1: Lab 4: Prepare Finance Data for Copilot in Excel
A3: Course | B3: Microsoft Copilot for Finance (TGS-2026065050)
A4: TSC mapping | B4: K1 · A2
A5: Objective | B5: Convert a messy finance export into an analysis-ready Excel Table with reconciled control totals.
A6: Scenario | B6: The FP&A team receives a mixed-quality export from the billing system. Copilot will answer confidently on dirty data, so the data must be fixed first.
A7: Expected output | B7: A clean transactions table, a quality log and reconciled control totals.
A8: Data notice | B8: All names, accounts, transactions and scores are synthetic. Do not replace them with live personal or customer data.
A9: Acceptance | B9: Duplicate count is zero, required-field errors are zero, cleaned totals reconcile to the control figures, and the before-and-after Copilot answers are documented.

Sheet Data Dictionary
A1: What each column means, and what "clean" looks like
A3: Column | B3: Expected type | C3: Rule
A4: JournalID | B4: Text | C4: Unique. Never edit an ID to fix a duplicate; investigate it.
A5: Period | B5: Text YYYY-MM | C5: Must match the posting date month.
A6: PostingDate | B6: Date | C6: A real date value, not text. Must fall in H1 FY2026.
A7: Department | B7: Text | C7: One of the four Northstar departments. Never blank.
A8: Region | B8: Text | C8: Singapore, Malaysia, Hong Kong or Australia.
A9: AccountCode | B9: Text | C9: Four digits. 4xxx is revenue; 5xxx-7xxx is cost.
A10: AmountSGD | B10: Number | C10: Revenue positive, cost negative. Never stored as text.
A11: Status | B11: Text | C11: Posted or Pending.

Sheet Transactions
A1: JournalID | B1: Period | C1: PostingDate | D1: Department | E1: Region | F1: AccountCode | G1: AmountSGD | H1: Status | I1: Required check | J1: Duplicate check | K1: Sign check
A2: JE-2026-00001 | B2: 2026-01 | C2: 46053 | D2: Retail Banking | E2: Singapore | F2: 4000 | G2: 778911.86 | H2: Posted | I2: =IF(OR(A2="",B2="",C2="",D2="",F2="",G2=""),"ERROR","OK") -> OK | J2: =IF(COUNTIF($A$2:$A$241,A2)>1,"DUPLICATE","OK") -> OK | K2: =IF(NOT(ISNUMBER(G2)),"NOT NUMBER",IF(OR(AND(LEFT(F2,1)="4",G2>=0),AND(LEFT(F2,1)<>"4",G2<=0)),"OK","CHECK")) -> OK
A3: JE-2026-00002 | B3: 2026-01 | C3: 46053 | D3: Retail Banking | E3: Singapore | F3: 4100 | G3: 385865.95 | H3: Posted | I3: =IF(OR(A3="",B3="",C3="",D3="",F3="",G3=""),"ERROR","OK") -> OK | J3: =IF(COUNTIF($A$2:$A$241,A3)>1,"DUPLICATE","OK") -> OK | K3: =IF(NOT(ISNUMBER(G3)),"NOT NUMBER",IF(OR(AND(LEFT(F3,1)="4",G3>=0),AND(LEFT(F3,1)<>"4",G3<=0)),"OK","CHECK")) -> OK
A4: JE-2026-00003 | B4: 2026-01 | C4: 46053 | D4: Retail Banking | E4: Singapore | F4: 4200 | G4: 245586.72 | H4: Posted | I4: =IF(OR(A4="",B4="",C4="",D4="",F4="",G4=""),"ERROR","OK") -> OK | J4: =IF(COUNTIF($A$2:$A$241,A4)>1,"DUPLICATE","OK") -> OK | K4: =IF(NOT(ISNUMBER(G4)),"NOT NUMBER",IF(OR(AND(LEFT(F4,1)="4",G4>=0),AND(LEFT(F4,1)<>"4",G4<=0)),"OK","CHECK")) -> OK
A5: JE-2026-00004 | B5: 2026-01 | C5: 46053 | D5: Retail Banking | E5: Singapore | F5: 5000 | G5: -402281.27 | H5: Posted | I5: =IF(OR(A5="",B5="",C5="",D5="",F5="",G5=""),"ERROR","OK") -> OK | J5: =IF(COUNTIF($A$2:$A$241,A5)>1,"DUPLICATE","OK") -> OK | K5: =IF(NOT(ISNUMBER(G5)),"NOT NUMBER",IF(OR(AND(LEFT(F5,1)="4",G5>=0),AND(LEFT(F5,1)<>"4",G5<=0)),"OK","CHECK")) -> OK
A6: JE-2026-00005 | B6: 2026-01 | C6: 46053 | D6: Retail Banking | E6: Singapore | F6: 6100 | G6: -121835.14 | H6: Posted | I6: =IF(OR(A6="",B6="",C6="",D6="",F6="",G6=""),"ERROR","OK") -> OK | J6: =IF(COUNTIF($A$2:$A$241,A6)>1,"DUPLICATE","OK") -> OK | K6: =IF(NOT(ISNUMBER(G6)),"NOT NUMBER",IF(OR(AND(LEFT(F6,1)="4",G6>=0),AND(LEFT(F6,1)<>"4",G6<=0)),"OK","CHECK")) -> OK
A7: JE-2026-00006 | B7: 2026-01 | C7: 46053 | D7: Retail Banking | E7: Singapore | F7: 6200 | G7: -159661.89 | H7: Posted | I7: =IF(OR(A7="",B7="",C7="",D7="",F7="",G7=""),"ERROR","OK") -> OK | J7: =IF(COUNTIF($A$2:$A$241,A7)>1,"DUPLICATE","OK") -> OK | K7: =IF(NOT(ISNUMBER(G7)),"NOT NUMBER",IF(OR(AND(LEFT(F7,1)="4",G7>=0),AND(LEFT(F7,1)<>"4",G7<=0)),"OK","CHECK")) -> OK
A8: JE-2026-00007 | B8: 2026-01 | C8: 46053 | D8: Retail Banking | E8: Singapore | F8: 6300 | G8: -353470.13 | H8: Posted | I8: =IF(OR(A8="",B8="",C8="",D8="",F8="",G8=""),"ERROR","OK") -> OK | J8: =IF(COUNTIF($A$2:$A$241,A8)>1,"DUPLICATE","OK") -> OK | K8: =IF(NOT(ISNUMBER(G8)),"NOT NUMBER",IF(OR(AND(LEFT(F8,1)="4",G8>=0),AND(LEFT(F8,1)<>"4",G8<=0)),"OK","CHECK")) -> OK
A9: JE-2026-00008 | B9: 2026-01 | C9: 46053 | D9: Retail Banking | E9: Singapore | F9: 6400 | G9: -76164.73 | H9: Posted | I9: =IF(OR(A9="",B9="",C9="",D9="",F9="",G9=""),"ERROR","OK") -> OK | J9: =IF(COUNTIF($A$2:$A$241,A9)>1,"DUPLICATE","OK") -> OK | K9: =IF(NOT(ISNUMBER(G9)),"NOT NUMBER",IF(OR(AND(LEFT(F9,1)="4",G9>=0),AND(LEFT(F9,1)<>"4",G9<=0)),"OK","CHECK")) -> OK
A10: JE-2026-00009 | B10: 2026-01 | C10: 46053 | D10: Retail Banking | E10: Singapore | F10: 6500 | G10: -55596.5 | H10: Posted | I10: =IF(OR(A10="",B10="",C10="",D10="",F10="",G10=""),"ERROR","OK") -> OK | J10: =IF(COUNTIF($A$2:$A$241,A10)>1,"DUPLICATE","OK") -> OK | K10: =IF(NOT(ISNUMBER(G10)),"NOT NUMBER",IF(OR(AND(LEFT(F10,1)="4",G10>=0),AND(LEFT(F10,1)<>"4",G10<=0)),"OK","CHECK")) -> OK
A11: JE-2026-00010 | B11: 2026-01 | C11: 46053 | D11: Retail Banking | E11: Singapore | F11: 7000 | G11: -43241.89 | H11: Posted | I11: =IF(OR(A11="",B11="",C11="",D11="",F11="",G11=""),"ERROR","OK") -> OK | J11: =IF(COUNTIF($A$2:$A$241,A11)>1,"DUPLICATE","OK") -> OK | K11: =IF(NOT(ISNUMBER(G11)),"NOT NUMBER",IF(OR(AND(LEFT(F11,1)="4",G11>=0),AND(LEFT(F11,1)<>"4",G11<=0)),"OK","CHECK")) -> OK
A12: JE-2026-00011 | B12: 2026-01 | C12: 46053 | D12: SME Lending | E12: Malaysia | F12: 4000 | G12: 581577.74 | H12: Posted | I12: =IF(OR(A12="",B12="",C12="",D12="",F12="",G12=""),"ERROR","OK") -> OK | J12: =IF(COUNTIF($A$2:$A$241,A12)>1,"DUPLICATE","OK") -> OK | K12: =IF(NOT(ISNUMBER(G12)),"NOT NUMBER",IF(OR(AND(LEFT(F12,1)="4",G12>=0),AND(LEFT(F12,1)<>"4",G12<=0)),"OK","CHECK")) -> OK
A13: JE-2026-00012 | B13: 2026-01 | C13: 46053 | D13: SME Lending | E13: Malaysia | F13: 4100 | G13: 295598.3 | H13: Posted | I13: =IF(OR(A13="",B13="",C13="",D13="",F13="",G13=""),"ERROR","OK") -> OK | J13: =IF(COUNTIF($A$2:$A$241,A13)>1,"DUPLICATE","OK") -> OK | K13: =IF(NOT(ISNUMBER(G13)),"NOT NUMBER",IF(OR(AND(LEFT(F13,1)="4",G13>=0),AND(LEFT(F13,1)<>"4",G13<=0)),"OK","CHECK")) -> OK
... A241: JE-2026-00240 | B241: 2026-06 | C241: 46203 | D241: Digital Payments | E241: Hong Kong | F241: 7000 | G241: -20266.46 | H241: Posted | I241: =IF(OR(A241="",B241="",C241="",D241="",F241="",G241=""),"ERROR","OK") -> OK | J241: =IF(COUNTIF($A$2:$A$241,A241)>1,"DUPLICATE","OK") -> OK | K241: =IF(NOT(ISNUMBER(G241)),"NOT NUMBER",IF(OR(AND(LEFT(F241,1)="4",G241>=0),AND(LEFT(F241,1)<>"4",G241<=0)),"OK","CHECK")) -> OK

Sheet Quality & Controls
A1: Control totals — the cleaned data must reconcile to these
A3: Control | B3: Your value | C3: Expected | D3: Note
A4: Row count | B4: =COUNTA(Transactions!A2:A241) -> 240 | C4: 240 | D4: No rows may be deleted
A5: Duplicate IDs | B5: =COUNTIF(Transactions!J2:J241,"DUPLICATE") -> 0 | C5: 0 | D5: Investigate, never renumber
A6: Required-field errors | B6: =COUNTIF(Transactions!I2:I241,"ERROR") -> 0 | C6: 0 | D6: Blank key fields
A7: Sign or type errors | B7: =COUNTIF(Transactions!K2:K241,"OK") -> 240 | C7: 240 | D7: Should equal the row count
A8: Revenue total | B8: =SUMIFS(Transactions!G2:G241,Transactions!F2:F241,"4*") -> 30402639 | C8: 30402639 | D8: Accounts 4000-4200
A9: Cost total | B9: =SUMIFS(Transactions!G2:G241,Transactions!F2:F241,"<>4*") -> -25635380 | C9: -25635380 | D9: Shown negative
A10: Net profit | B10: =SUM(Transactions!G2:G241) -> 4767259.4 | C10: 4767259.4 | D10: Must equal the control total

Sheet Copilot Comparison
A1: The same question, before and after cleaning
A2: Ask Copilot the same question on the dirty table and the clean one. Record both answers.
A5: Question | B5: Answer on the dirty table | C5: Answer on the clean table
A6: Which department had the highest total cost?
A7: What is total revenue for the period?
A8: Are there any data quality problems I should know about?
