Workbook

Sheet Start Here
A1: Lab 6: Reconcile Accounts and Forecast with Copilot
A3: Course | B3: Microsoft Copilot for Finance (TGS-2026065050)
A4: TSC mapping | B4: K1 · A2
A5: Objective | B5: Apply deterministic matching rules and build a driver-based forecast with scenarios.
A6: Scenario | B6: The controller must reconcile the bank statement to the receivables ledger and produce a defensible H2 forecast.
A7: Expected output | B7: A reconciliation report with an owned exception queue and a base, downside and upside forecast.
A8: Data notice | B8: All names, accounts, transactions and scores are synthetic. Do not replace them with live personal or customer data.
A9: Acceptance | B9: Matched plus exception values reconcile to both sources; every unresolved item has a reason, age and owner; scenarios are driven by assumption cells; escalation items above the policy threshold are flagged.

Sheet Match Rules
A1: Match rules from POL-FIN-002 Month-End Close Calendar and Controls
A3: Classification | B3: Definition
A4: Exact match | B4: The amount and the reference both agree.
A5: Tolerance match | B5: The amount differs by SGD 50 or less. Note it; a reviewer clears it.
A6: Reference-only match | B6: The amount agrees but the bank narrative lost the invoice ID. Always needs reviewer confirmation.
A7: Exception | B7: Anything else. Must be aged, owned and explained.
A8: Escalation | B8: Unreconciled items above SGD 10,000 or older than 60 days go to the Financial Controller.

Sheet AR Ledger
A1: InvoiceID | B1: CustomerID | C1: CustomerName | D1: Department | E1: InvoiceDate | F1: DueDate | G1: InvoiceAmountSGD | H1: OutstandingSGD | I1: DaysOverdue | J1: AgeingBucket | K1: CollectionStatus
A2: INV-2026-0001 | B2: CUST-005 | C2: Kowloon Digital Ltd | D2: Digital Payments | E2: 46134 | F2: 46164 | G2: 353357.82 | H2: 353357.82 | I2: 39 | J2: 31-60 days | K2: Follow-up
A3: INV-2026-0002 | B3: CUST-006 | C3: Sydney Freight Co | D3: Enterprise | E3: 46107 | F3: 46137 | G3: 644172.69 | H3: 644172.69 | I3: 66 | J3: 61-90 days | K3: Escalated
A4: INV-2026-0003 | B4: CUST-005 | C4: Kowloon Digital Ltd | D4: Digital Payments | E4: 46094 | F4: 46139 | G4: 604077.9 | H4: 604077.9 | I4: 64 | J4: 61-90 days | K4: Escalated
A5: INV-2026-0004 | B5: CUST-006 | C5: Sydney Freight Co | D5: Enterprise | E5: 46191 | F5: 46236 | G5: 719003.82 | H5: 0 | I5: 0 | J5: Current | K5: Paid
A6: INV-2026-0005 | B6: CUST-008 | C6: Johor Agri Holdings | D6: SME Lending | E6: 46118 | F6: 46148 | G6: 365123.27 | H6: 365123.27 | I6: 55 | J6: 31-60 days | K6: Follow-up
A7: INV-2026-0006 | B7: CUST-011 | C7: Tampines Medical Group | D7: Enterprise | E7: 46131 | F7: 46191 | G7: 155472.05 | H7: 155472.05 | I7: 12 | J7: 1-30 days | K7: Follow-up
A8: INV-2026-0007 | B8: CUST-010 | C8: Victoria Payments Pty | D8: Digital Payments | E8: 46088 | F8: 46148 | G8: 278459.79 | H8: 278459.79 | I8: 55 | J8: 31-60 days | K8: Follow-up
A9: INV-2026-0008 | B9: CUST-008 | C9: Johor Agri Holdings | D9: SME Lending | E9: 46150 | F9: 46195 | G9: 596992.6 | H9: 596992.6 | I9: 8 | J9: 1-30 days | K9: Follow-up
A10: INV-2026-0009 | B10: CUST-004 | C10: Harbourfront Retail Group | D10: Retail Banking | E10: 46154 | F10: 46184 | G10: 387523.41 | H10: 387523.41 | I10: 19 | J10: 1-30 days | K10: Follow-up
A11: INV-2026-0010 | B11: CUST-001 | C11: Marina Bay Logistics | D11: Enterprise | E11: 46151 | F11: 46196 | G11: 409661.5 | H11: 409661.5 | I11: 7 | J11: 1-30 days | K11: Follow-up
A12: INV-2026-0011 | B12: CUST-001 | C12: Marina Bay Logistics | D12: Enterprise | E12: 46164 | F12: 46194 | G12: 137396.82 | H12: 137396.82 | I12: 9 | J12: 1-30 days | K12: Follow-up
A13: INV-2026-0012 | B13: CUST-006 | C13: Sydney Freight Co | D13: Enterprise | E13: 46197 | F13: 46257 | G13: 267272.97 | H13: 267272.97 | I13: 0 | J13: Current | K13: Not due
... A34: INV-2026-0033 | B34: CUST-010 | C34: Victoria Payments Pty | D34: Digital Payments | E34: 46194 | F34: 46239 | G34: 321048.76 | H34: 0 | I34: 0 | J34: Current | K34: Paid

Sheet Bank Statement
A1: BankTxnID | B1: ValueDate | C1: Description | D1: CreditSGD | E1: DebitSGD | F1: Reference | G1: Classification | H1: Reason / owner
A2: BNK-2026-00001 | B2: 46203 | C2: RCPT Sydney Freight Co | D2: 719003.82 | E2: 0 | F2: INV-2026-0004 | G2: Exact match | H2: Amount and reference agree
A3: BNK-2026-00002 | B3: 46203 | C3: RCPT Tampines Medical G | D3: 120618.6 | E3: 0 | F3: INV-2026-0014 | G3: Exact match | H3: Amount and reference agree
A4: BNK-2026-00003 | B4: 46203 | C4: RCPT Victoria Payments | D4: 612252.14 | E4: 0 | F4: INV-2026-0019 | G4: Exact match | H4: Amount and reference agree
A5: BNK-2026-00004 | B5: 46203 | C5: RCPT Marina Bay Logisti | D5: 270735.55 | E5: 0 | G5: Reference-only match | H5: Amount agrees but the narrative lost the invoice ID; reviewer confirms
A6: BNK-2026-00005 | B6: 46203 | C6: RCPT Victoria Payments | D6: 289901.12 | E6: 0 | F6: INV-2026-0023 | G6: Exact match | H6: Amount and reference agree
A7: BNK-2026-00006 | B7: 46203 | C7: RCPT Tampines Medical G | D7: 571736.47 | E7: 0 | F7: INV-2026-0024 | G7: Tolerance match | H7: Short paid by SGD 26.77; within tolerance, reviewer clears
A8: BNK-2026-00007 | B8: 46203 | C8: RCPT Orchard Lifestyle | D8: 355535.81 | E8: 0 | F8: INV-2026-0026 | G8: Exact match | H8: Amount and reference agree
A9: BNK-2026-00008 | B9: 46203 | C9: RCPT Victoria Payments | D9: 361321.14 | E9: 0 | F9: INV-2026-0027 | G9: Exact match | H9: Amount and reference agree
A10: BNK-2026-00009 | B10: 46203 | C10: RCPT Melaka Shipping | D10: 166254.45 | E10: 0 | F10: INV-2026-0030 | G10: Exact match | H10: Amount and reference agree
A11: BNK-2026-00010 | B11: 46203 | C11: RCPT Harbourfront Retai | D11: 317088.77 | E11: 0 | F11: INV-2026-0032 | G11: Exact match | H11: Amount and reference agree
A12: BNK-2026-00011 | B12: 46203 | C12: RCPT Victoria Payments | D12: 321048.76 | E12: 0 | G12: Reference-only match | H12: Amount agrees but the narrative lost the invoice ID; reviewer confirms
A13: BNK-2026-00012 | B13: 46193 | C13: BANK CHARGES | D13: 0 | E13: 938.82 | G13: Exception | H13: Bank-only item; investigate and explain
A14: BNK-2026-00013 | B14: 46201 | C14: FX ADJUSTMENT | D14: 0 | E14: 271.42 | G14: Exception | H14: Bank-only item; investigate and explain
A15: BNK-2026-00014 | B15: 46179 | C15: RETURNED PAYMENT | D15: 0 | E15: 1421.44 | G15: Exception | H15: Bank-only item; investigate and explain
A16: BNK-2026-00015 | B16: 46202 | C16: INTEREST CREDIT | D16: 2198.68 | E16: 0 | G16: Exception | H16: Bank-only item; investigate and explain
A17: BNK-2026-00016 | B17: 46200 | C17: UNIDENTIFIED RECEIPT | D17: 5351.44 | E17: 0 | G17: Exception | H17: Bank-only item; investigate and explain
A18: BNK-2026-00017 | B18: 46200 | C18: MERCHANT SETTLEMENT | D18: 7185.54 | E18: 0 | G18: Exception | H18: Bank-only item; investigate and explain

Sheet Ageing Profile
A1: Ageing bucket | B1: Invoices | C1: Outstanding SGD
A2: Current | B2: 15 | C2: 1542432.6
A3: 1-30 days | B3: 7 | C3: 2798224.9
A4: 31-60 days | B4: 8 | C4: 2855308
A5: 61-90 days | B5: 3 | C5: 1768725.6

Sheet Reconciliation
A1: Reconciliation summary
A3: Measure | B3: Value | C3: Check | D3: Note
A4: Bank lines | B4: =COUNTA('Bank Statement'!A2:A18) -> 17 | C4: 17 | D4: Every line must be classified
A5: Total credits | B5: =SUM('Bank Statement'!D2:D18) -> 4120232.3 | C5: 4120232.3 | D5: Money in
A6: Total debits | B6: =SUM('Bank Statement'!E2:E18) -> 2631.68 | C6: 2631.68 | D6: Money out
A7: Lines classified | B7: =COUNTA('Bank Statement'!G2:G18) -> 17 | C7: 17 | D7: Must equal bank lines
A8: Exceptions | B8: =COUNTIF('Bank Statement'!G2:G18,"Exception") -> 0 | D8: Each needs an age and an owner

Sheet Forecast Assumptions
A1: Drive the forecast from these cells — never hard-code an output
A3: Assumption | B3: Base | C3: Unit | D3: Owner
A4: Monthly revenue growth | B4: 0.018 | C4: % | D4: FP&A Manager
A5: Cost inflation per month | B5: 0.011 | C5: % | D5: FP&A Manager
A6: Downside revenue factor | B6: 0.93 | C6: x | D6: CFO
A7: Upside revenue factor | B7: 1.06 | C7: x | D7: CFO
A8: Collection days | B8: 45 | C8: days | D8: AR Manager

Sheet Forecast
A1: H2 FY2026 forecast — three coherent scenarios
A3: Month | B3: Downside | C3: Base | D3: Upside
A4: Jul | B4: =C4*'Forecast Assumptions'!$B$6 -> 757392 | C4: =800000.0*(1+'Forecast Assumptions'!$B$4)^1 -> 814400 | D4: =C4*'Forecast Assumptions'!$B$7 -> 863264
A5: Aug | B5: =C5*'Forecast Assumptions'!$B$6 -> 771025.06 | C5: =800000.0*(1+'Forecast Assumptions'!$B$4)^2 -> 829059.2 | D5: =C5*'Forecast Assumptions'!$B$7 -> 878802.75
A6: Sep | B6: =C6*'Forecast Assumptions'!$B$6 -> 784903.51 | C6: =800000.0*(1+'Forecast Assumptions'!$B$4)^3 -> 843982.27 | D6: =C6*'Forecast Assumptions'!$B$7 -> 894621.2
A7: Oct | B7: =C7*'Forecast Assumptions'!$B$6 -> 799031.77 | C7: =800000.0*(1+'Forecast Assumptions'!$B$4)^4 -> 859173.95 | D7: =C7*'Forecast Assumptions'!$B$7 -> 910724.38
A8: Nov | B8: =C8*'Forecast Assumptions'!$B$6 -> 813414.34 | C8: =800000.0*(1+'Forecast Assumptions'!$B$4)^5 -> 874639.08 | D8: =C8*'Forecast Assumptions'!$B$7 -> 927117.42
A9: Dec | B9: =C9*'Forecast Assumptions'!$B$6 -> 828055.8 | C9: =800000.0*(1+'Forecast Assumptions'!$B$4)^6 -> 890382.58 | D9: =C9*'Forecast Assumptions'!$B$7 -> 943805.54
